photutils/CITATION.rst
photutils/__init__.py
photutils/compiler_version.cpython-313-x86_64-linux-gnu.so
photutils/conftest.py
photutils/version.py
photutils/aperture/__init__.py
photutils/aperture/attributes.py
photutils/aperture/bounding_box.py
photutils/aperture/circle.py
photutils/aperture/converters.py
photutils/aperture/core.py
photutils/aperture/ellipse.py
photutils/aperture/mask.py
photutils/aperture/photometry.py
photutils/aperture/rectangle.py
photutils/aperture/stats.py
photutils/aperture/tests/__init__.py
photutils/aperture/tests/test_aperture_common.py
photutils/aperture/tests/test_bounding_box.py
photutils/aperture/tests/test_circle.py
photutils/aperture/tests/test_converters.py
photutils/aperture/tests/test_ellipse.py
photutils/aperture/tests/test_mask.py
photutils/aperture/tests/test_photometry.py
photutils/aperture/tests/test_rectangle.py
photutils/aperture/tests/test_stats.py
photutils/background/__init__.py
photutils/background/background_2d.py
photutils/background/core.py
photutils/background/interpolators.py
photutils/background/local_background.py
photutils/background/tests/__init__.py
photutils/background/tests/test_background_2d.py
photutils/background/tests/test_core.py
photutils/background/tests/test_interpolators.py
photutils/background/tests/test_local_background.py
photutils/centroids/__init__.py
photutils/centroids/core.py
photutils/centroids/gaussian.py
photutils/centroids/tests/__init__.py
photutils/centroids/tests/test_core.py
photutils/centroids/tests/test_gaussian.py
photutils/datasets/__init__.py
photutils/datasets/examples.py
photutils/datasets/images.py
photutils/datasets/load.py
photutils/datasets/model_params.py
photutils/datasets/noise.py
photutils/datasets/wcs.py
photutils/datasets/data/100gaussians_params.ecsv
photutils/datasets/data/4gaussians_params.ecsv
photutils/datasets/tests/__init__.py
photutils/datasets/tests/test_examples.py
photutils-2.3.0.dist-info/METADATA
photutils-2.3.0.dist-info/WHEEL
photutils-2.3.0.dist-info/top_level.txt
photutils-2.3.0.dist-info/RECORD
photutils-2.3.0.dist-info/licenses/LICENSE.rst
