Metadata-Version: 2.4
Name: photutils
Version: 2.3.0
Summary: An Astropy package for source detection and photometry
Author-email: Photutils Developers <astropy.team@gmail.com>
License-Expression: BSD-3-Clause
Project-URL: Homepage, https://github.com/astropy/photutils
Project-URL: Documentation, https://photutils.readthedocs.io/en/stable/
Keywords: astronomy,astrophysics,photometry,aperture,psf,source detection,background,segmentation,centroids,isophote,morphology,radial profiles
Classifier: Intended Audience :: Science/Research
Classifier: Natural Language :: English
Classifier: Operating System :: OS Independent
Classifier: Programming Language :: Cython
Classifier: Programming Language :: Python
Classifier: Programming Language :: Python :: 3
Classifier: Topic :: Scientific/Engineering :: Astronomy
Requires-Python: >=3.11
License-File: LICENSE.rst
Requires-Dist: numpy>=1.25
Requires-Dist: astropy>=5.3
Requires-Dist: scipy>=1.11.1
Provides-Extra: all
Requires-Dist: matplotlib>=3.8; extra == "all"
Requires-Dist: regions>=0.9; extra == "all"
Requires-Dist: scikit-image>=0.21; extra == "all"
Requires-Dist: gwcs>=0.20; extra == "all"
Requires-Dist: bottleneck>=1.3.6; extra == "all"
Requires-Dist: tqdm>=4.65; extra == "all"
Requires-Dist: rasterio>=1.3.7; extra == "all"
Requires-Dist: shapely>=2.0.0; extra == "all"
Provides-Extra: test
Requires-Dist: pytest-astropy>=0.11; extra == "test"
Requires-Dist: pytest-xdist>=2.5.0; extra == "test"
Requires-Dist: tox>4.0; extra == "test"
Provides-Extra: docs
Requires-Dist: photutils[all]; extra == "docs"
Requires-Dist: sphinx; extra == "docs"
Requires-Dist: sphinx_design; extra == "docs"
Requires-Dist: sphinx-astropy[confv2]>=1.9.1; extra == "docs"
Provides-Extra: dev
Requires-Dist: photutils[docs,test]; extra == "dev"
Requires-Dist: pre-commit>4.0; extra == "dev"
Dynamic: license-file
